{
    "uuid": "4591f76f-f638-43be-8e2d-a60b292e3674",
    "type": "Exam",
    "title": "Exam 3",
    "set": "Exam",
    "module": "Module3",
    "number": "3",
    "allowAccess": [
        {
            "mode": "Exam",
            "credit": 100,
            "startDate": "1900-07-07T23:59:59",
            "endDate": "2300-07-10T23:59:59",
            "timeLimitMin": 50
        }
    ],
    "zones": [
        {
            "title": "Hard questions",
            "questions": [
                {"id": "addVectors",                 "points": [10, 5, 1]},
                {"id": "positionTimeGraph",          "points": [10]}
            ]
        }
    ]
}
